todus/__init__.py
todus/__main__.py
todus/client.py
todus/errors.py
todus/main.py
todus/util.py
todus-1.1.0.dist-info/LICENSE
todus-1.1.0.dist-info/METADATA
todus-1.1.0.dist-info/WHEEL
todus-1.1.0.dist-info/entry_points.txt
todus-1.1.0.dist-info/top_level.txt
todus-1.1.0.dist-info/RECORD
