Metadata-Version: 2.1
Name: todus
Version: 1.1.0
Summary: ToDus client
Home-page: https://github.com/adbenitez/todus
Author: adbenitez
Author-email: adbenitez@nauta.cu
License: MPL
Keywords: todus
Platform: UNKNOWN
Classifier: Development Status :: 4 - Beta
Classifier: Programming Language :: Python :: 3
Classifier: License :: OSI Approved :: Mozilla Public License 2.0 (MPL 2.0)
Classifier: Operating System :: OS Independent
Classifier: Topic :: Utilities
License-File: LICENSE
Requires-Dist: requests (>=2.26.0)
Requires-Dist: multivolumefile (>=0.2.3)
Requires-Dist: tqdm (>=4.62.2)
Provides-Extra: 7z
Requires-Dist: requests (>=2.26.0) ; extra == '7z'
Requires-Dist: multivolumefile (>=0.2.3) ; extra == '7z'
Requires-Dist: tqdm (>=4.62.2) ; extra == '7z'
Requires-Dist: py7zr (>=0.16.1) ; extra == '7z'
Provides-Extra: dev
Requires-Dist: requests (>=2.26.0) ; extra == 'dev'
Requires-Dist: multivolumefile (>=0.2.3) ; extra == 'dev'
Requires-Dist: tqdm (>=4.62.2) ; extra == 'dev'
Requires-Dist: pytest (>=6.2.5) ; extra == 'dev'
Requires-Dist: black (>=21.8b0) ; extra == 'dev'
Requires-Dist: mypy (>=0.910) ; extra == 'dev'
Requires-Dist: isort (>=5.9.3) ; extra == 'dev'
Requires-Dist: pylint (>=2.10.2) ; extra == 'dev'
Requires-Dist: pylama (>=7.7.1) ; extra == 'dev'
Requires-Dist: types-pkg-resources (>=0.1.3) ; extra == 'dev'
Requires-Dist: types-requests (>=2.25.6) ; extra == 'dev'
Provides-Extra: test
Requires-Dist: pytest (>=6.2.5) ; extra == 'test'
